LICENSE.txt
README.md
setup.py
radicale_storage_decsync/__init__.py
radicale_storage_decsync.egg-info/PKG-INFO
radicale_storage_decsync.egg-info/SOURCES.txt
radicale_storage_decsync.egg-info/dependency_links.txt
radicale_storage_decsync.egg-info/requires.txt
radicale_storage_decsync.egg-info/top_level.txt