Metadata-Version: 2.1
Name: radicale-storage-decsync
Version: 1.2.2
Summary: DecSync storage plugin for Radicale
Home-page: https://github.com/39aldo39/Radicale-DecSync
Author: Aldo Gunsing
Author-email: dev@aldogunsing.nl
License: GPLv3+
Keywords: decsync,radicale
Platform: UNKNOWN
Classifier: Programming Language :: Python :: 3
Classifier: Operating System :: POSIX :: Linux
Classifier: Operating System :: Microsoft :: Windows
Classifier: License :: OSI Approved :: GNU General Public License v3 or later (GPLv3+)
Classifier: Intended Audience :: End Users/Desktop
